onlinepvt/__init__.py
onlinepvt/online_pvt_client.py
onlinepvt/types.py
onlinepvt/demofluids/__init__.py
onlinepvt/demofluids/fluids.py
onlinepvt/models/__init__.py
onlinepvt/models/api_call_result.py
onlinepvt/models/api_fluid.py
onlinepvt/models/api_fluid_component_block.py
onlinepvt/models/api_fluid_distribution_moment.py
onlinepvt/models/api_fluid_kij.py
onlinepvt/models/api_fluid_polymer_component.py
onlinepvt/models/api_fluid_pseudo_component.py
onlinepvt/models/api_fluid_standard_component.py
onlinepvt/models/api_output_calculation_result_phase.py
onlinepvt/models/api_output_calculation_result_phase_composition.py
onlinepvt/models/api_output_calculation_result_phase_polymer_moment.py
onlinepvt/models/api_output_calculation_result_phase_polymer_moments.py
onlinepvt/models/api_output_calculation_result_point.py
onlinepvt/models/api_output_phasediagram.py
onlinepvt/models/api_output_phasediagram_point.py
onlinepvt/models/api_output_unflashed_property_result.py
onlinepvt/models/api_output_unflashed_property_result_ideal.py
onlinepvt/models/api_output_unflashed_property_result_residual.py
onlinepvt/models/api_profile_information.py
onlinepvt/models/api_profile_time_information.py
onlinepvt/models/api_value_component_composition.py
onlinepvt/models/api_value_composition_array.py
onlinepvt/models/api_value_compressibility.py
onlinepvt/models/api_value_density.py
onlinepvt/models/api_value_enthalpy.py
onlinepvt/models/api_value_entropy.py
onlinepvt/models/api_value_floating_with_out_units.py
onlinepvt/models/api_value_floating_with_out_units_name.py
onlinepvt/models/api_value_floating_with_units.py
onlinepvt/models/api_value_mole_percent.py
onlinepvt/models/api_value_pressure.py
onlinepvt/models/api_value_temperature.py
onlinepvt/models/api_value_volume.py
onlinepvt/models/api_value_weight_percent.py
onlinepvt/models/association_scheme.py
onlinepvt/models/calculation_block_info.py
onlinepvt/models/calculation_composition.py
VLXE-0.0.1.dist-info/LICENSE
VLXE-0.0.1.dist-info/METADATA
VLXE-0.0.1.dist-info/WHEEL
VLXE-0.0.1.dist-info/top_level.txt
VLXE-0.0.1.dist-info/RECORD
