Metadata-Version: 2.1
Name: VLXE
Version: 0.0.1
Summary: Python SDK for accessing OnlinePVT API
Home-page: https://github.com/OnlinePVT/onlinepvt-python-sdk
Author: VLXE A/S
Author-email: tl@vlxe.com
Project-URL: Bug Tracker, https://github.com/OnlinePVT/onlinepvt-python-sdk/issues
Classifier: Programming Language :: Python :: 3
Classifier: License :: OSI Approved :: MIT License
Classifier: Operating System :: OS Independent
Requires-Python: >=3.6
License-File: LICENSE
